LICENSE
README.md
setup.py
SteamedBread_Uninstall.egg-info/PKG-INFO
SteamedBread_Uninstall.egg-info/SOURCES.txt
SteamedBread_Uninstall.egg-info/dependency_links.txt
SteamedBread_Uninstall.egg-info/entry_points.txt
SteamedBread_Uninstall.egg-info/top_level.txt
_CleanPackageTools/CleanDependence.py
_CleanPackageTools/__init__.py